{
    "name": "App\\MessengerMessage",
    "line": 10,
    "short_desc": "",
    "long_desc": "",
    "hint": null,
    "tags": [],
    "namespace": "App",
    "file": "\/home\/vagrant\/repos\/cms\/configuration2\/app\/MessengerMessage.php",
    "relative_file": null,
    "hash": "c3737ddaebf8e2f1459b7a77a1a5d95ba89c05ce",
    "parent": "Illuminate\\Database\\Eloquent\\Model",
    "modifiers": 0,
    "is_trait": false,
    "is_interface": false,
    "aliases": {
        "Model": "Illuminate\\Database\\Eloquent\\Model",
        "MessengerTopic": "App\\MessengerTopic",
        "SoftDeletes": "Illuminate\\Database\\Eloquent\\SoftDeletes",
        "Auth": "Illuminate\\Support\\Facades\\Auth"
    },
    "errors": [],
    "interfaces": [],
    "traits": {
        "Illuminate\\Database\\Eloquent\\SoftDeletes": "Illuminate\\Database\\Eloquent\\SoftDeletes"
    },
    "properties": {
        "fillable": {
            "name": "fillable",
            "line": 14,
            "short_desc": "",
            "long_desc": "",
            "hint": null,
            "hint_desc": null,
            "tags": [],
            "modifiers": 2,
            "default": {
                "nodeType": "Expr_Array",
                "items": [
                    {
                        "nodeType": "Expr_ArrayItem",
                        "key": null,
                        "value": {
                            "nodeType": "Scalar_String",
                            "value": "topic_id",
                            "attributes": {
                                "startLine": 15,
                                "endLine": 15,
                                "kind": 1
                            }
                        },
                        "byRef": false,
                        "attributes": {
                            "startLine": 15,
                            "endLine": 15
                        }
                    },
                    {
                        "nodeType": "Expr_ArrayItem",
                        "key": null,
                        "value": {
                            "nodeType": "Scalar_String",
                            "value": "sender_id",
                            "attributes": {
                                "startLine": 16,
                                "endLine": 16,
                                "kind": 1
                            }
                        },
                        "byRef": false,
                        "attributes": {
                            "startLine": 16,
                            "endLine": 16
                        }
                    },
                    {
                        "nodeType": "Expr_ArrayItem",
                        "key": null,
                        "value": {
                            "nodeType": "Scalar_String",
                            "value": "content",
                            "attributes": {
                                "startLine": 17,
                                "endLine": 17,
                                "kind": 1
                            }
                        },
                        "byRef": false,
                        "attributes": {
                            "startLine": 17,
                            "endLine": 17
                        }
                    }
                ],
                "attributes": {
                    "startLine": 14,
                    "endLine": 18,
                    "kind": 2
                }
            },
            "errors": []
        },
        "dates": {
            "name": "dates",
            "line": 19,
            "short_desc": "",
            "long_desc": "",
            "hint": null,
            "hint_desc": null,
            "tags": [],
            "modifiers": 2,
            "default": {
                "nodeType": "Expr_Array",
                "items": [
                    {
                        "nodeType": "Expr_ArrayItem",
                        "key": null,
                        "value": {
                            "nodeType": "Scalar_String",
                            "value": "sent_at",
                            "attributes": {
                                "startLine": 20,
                                "endLine": 20,
                                "kind": 1
                            }
                        },
                        "byRef": false,
                        "attributes": {
                            "startLine": 20,
                            "endLine": 20
                        }
                    }
                ],
                "attributes": {
                    "startLine": 19,
                    "endLine": 21,
                    "kind": 2
                }
            },
            "errors": []
        },
        "with": {
            "name": "with",
            "line": 22,
            "short_desc": "",
            "long_desc": "",
            "hint": null,
            "hint_desc": null,
            "tags": [],
            "modifiers": 1,
            "default": {
                "nodeType": "Expr_Array",
                "items": [
                    {
                        "nodeType": "Expr_ArrayItem",
                        "key": null,
                        "value": {
                            "nodeType": "Scalar_String",
                            "value": "sender",
                            "attributes": {
                                "startLine": 22,
                                "endLine": 22,
                                "kind": 1
                            }
                        },
                        "byRef": false,
                        "attributes": {
                            "startLine": 22,
                            "endLine": 22
                        }
                    }
                ],
                "attributes": {
                    "startLine": 22,
                    "endLine": 22,
                    "kind": 2
                }
            },
            "errors": []
        }
    },
    "methods": {
        "topic": {
            "name": "topic",
            "line": 25,
            "short_desc": "",
            "long_desc": "",
            "hint": null,
            "hint_desc": null,
            "tags": [],
            "modifiers": 1,
            "is_by_ref": "",
            "exceptions": [],
            "errors": [],
            "parameters": []
        },
        "sender": {
            "name": "sender",
            "line": 30,
            "short_desc": "",
            "long_desc": "",
            "hint": null,
            "hint_desc": null,
            "tags": [],
            "modifiers": 1,
            "is_by_ref": "",
            "exceptions": [],
            "errors": [],
            "parameters": []
        },
        "unread": {
            "name": "unread",
            "line": 35,
            "short_desc": "",
            "long_desc": "",
            "hint": null,
            "hint_desc": null,
            "tags": [],
            "modifiers": 1,
            "is_by_ref": "",
            "exceptions": [],
            "errors": [],
            "parameters": {
                "topic": {
                    "name": "topic",
                    "line": 35,
                    "short_desc": null,
                    "long_desc": null,
                    "hint": null,
                    "tags": [],
                    "modifiers": null,
                    "default": null,
                    "variadic": false,
                    "is_by_ref": false
                }
            }
        }
    },
    "constants": []
}