{
    "name": "App\\Instance",
    "line": 21,
    "short_desc": "Class Instance",
    "long_desc": "",
    "hint": null,
    "tags": {
        "package": [
            [
                "App"
            ]
        ],
        "property": [
            [
                [
                    [
                        "string",
                        false
                    ]
                ],
                "group",
                ""
            ],
            [
                [
                    [
                        "integer",
                        false
                    ]
                ],
                "quantity_to_create",
                ""
            ],
            [
                [
                    [
                        "string",
                        false
                    ]
                ],
                "role_convention",
                ""
            ],
            [
                [
                    [
                        "string",
                        false
                    ]
                ],
                "channel_server",
                ""
            ],
            [
                [
                    [
                        "string",
                        false
                    ]
                ],
                "aggregation_server",
                ""
            ],
            [
                [
                    [
                        "string",
                        false
                    ]
                ],
                "env",
                ""
            ],
            [
                [
                    [
                        "\\App\\text",
                        false
                    ]
                ],
                "details",
                ""
            ],
            [
                [
                    [
                        "\\App\\text",
                        false
                    ]
                ],
                "notes",
                ""
            ],
            [
                [
                    [
                        "string",
                        false
                    ]
                ],
                "cs_token",
                ""
            ]
        ]
    },
    "namespace": "App",
    "file": "\/home\/vagrant\/repos\/cms\/configuration2\/app\/Instance.php",
    "relative_file": null,
    "hash": "c1dbeaacab6c43a8c3cfe968d0ff8d4cfe90d638",
    "parent": "Illuminate\\Database\\Eloquent\\Model",
    "modifiers": 0,
    "is_trait": false,
    "is_interface": false,
    "aliases": {
        "Model": "Illuminate\\Database\\Eloquent\\Model",
        "SoftDeletes": "Illuminate\\Database\\Eloquent\\SoftDeletes"
    },
    "errors": [],
    "interfaces": [],
    "traits": {
        "Illuminate\\Database\\Eloquent\\SoftDeletes": "Illuminate\\Database\\Eloquent\\SoftDeletes"
    },
    "properties": {
        "fillable": {
            "name": "fillable",
            "line": 25,
            "short_desc": "",
            "long_desc": "",
            "hint": null,
            "hint_desc": null,
            "tags": [],
            "modifiers": 2,
            "default": {
                "nodeType": "Expr_Array",
                "items": [
                    {
                        "nodeType": "Expr_ArrayItem",
                        "key": null,
                        "value": {
                            "nodeType": "Scalar_String",
                            "value": "quantity_to_create",
                            "attributes": {
                                "startLine": 25,
                                "endLine": 25,
                                "kind": 1
                            }
                        },
                        "byRef": false,
                        "attributes": {
                            "startLine": 25,
                            "endLine": 25
                        }
                    },
                    {
                        "nodeType": "Expr_ArrayItem",
                        "key": null,
                        "value": {
                            "nodeType": "Scalar_String",
                            "value": "details",
                            "attributes": {
                                "startLine": 25,
                                "endLine": 25,
                                "kind": 1
                            }
                        },
                        "byRef": false,
                        "attributes": {
                            "startLine": 25,
                            "endLine": 25
                        }
                    },
                    {
                        "nodeType": "Expr_ArrayItem",
                        "key": null,
                        "value": {
                            "nodeType": "Scalar_String",
                            "value": "notes",
                            "attributes": {
                                "startLine": 25,
                                "endLine": 25,
                                "kind": 1
                            }
                        },
                        "byRef": false,
                        "attributes": {
                            "startLine": 25,
                            "endLine": 25
                        }
                    },
                    {
                        "nodeType": "Expr_ArrayItem",
                        "key": null,
                        "value": {
                            "nodeType": "Scalar_String",
                            "value": "cs_token",
                            "attributes": {
                                "startLine": 25,
                                "endLine": 25,
                                "kind": 1
                            }
                        },
                        "byRef": false,
                        "attributes": {
                            "startLine": 25,
                            "endLine": 25
                        }
                    },
                    {
                        "nodeType": "Expr_ArrayItem",
                        "key": null,
                        "value": {
                            "nodeType": "Scalar_String",
                            "value": "group_id",
                            "attributes": {
                                "startLine": 25,
                                "endLine": 25,
                                "kind": 1
                            }
                        },
                        "byRef": false,
                        "attributes": {
                            "startLine": 25,
                            "endLine": 25
                        }
                    },
                    {
                        "nodeType": "Expr_ArrayItem",
                        "key": null,
                        "value": {
                            "nodeType": "Scalar_String",
                            "value": "role_convention_id",
                            "attributes": {
                                "startLine": 25,
                                "endLine": 25,
                                "kind": 1
                            }
                        },
                        "byRef": false,
                        "attributes": {
                            "startLine": 25,
                            "endLine": 25
                        }
                    },
                    {
                        "nodeType": "Expr_ArrayItem",
                        "key": null,
                        "value": {
                            "nodeType": "Scalar_String",
                            "value": "channel_server_id",
                            "attributes": {
                                "startLine": 25,
                                "endLine": 25,
                                "kind": 1
                            }
                        },
                        "byRef": false,
                        "attributes": {
                            "startLine": 25,
                            "endLine": 25
                        }
                    },
                    {
                        "nodeType": "Expr_ArrayItem",
                        "key": null,
                        "value": {
                            "nodeType": "Scalar_String",
                            "value": "aggregation_server_id",
                            "attributes": {
                                "startLine": 25,
                                "endLine": 25,
                                "kind": 1
                            }
                        },
                        "byRef": false,
                        "attributes": {
                            "startLine": 25,
                            "endLine": 25
                        }
                    },
                    {
                        "nodeType": "Expr_ArrayItem",
                        "key": null,
                        "value": {
                            "nodeType": "Scalar_String",
                            "value": "env_id",
                            "attributes": {
                                "startLine": 25,
                                "endLine": 25,
                                "kind": 1
                            }
                        },
                        "byRef": false,
                        "attributes": {
                            "startLine": 25,
                            "endLine": 25
                        }
                    }
                ],
                "attributes": {
                    "startLine": 25,
                    "endLine": 25,
                    "kind": 2
                }
            },
            "errors": []
        },
        "hidden": {
            "name": "hidden",
            "line": 27,
            "short_desc": "",
            "long_desc": "",
            "hint": null,
            "hint_desc": null,
            "tags": [],
            "modifiers": 2,
            "default": {
                "nodeType": "Expr_Array",
                "items": [],
                "attributes": {
                    "startLine": 27,
                    "endLine": 27,
                    "kind": 2
                }
            },
            "errors": []
        },
        "searchable": {
            "name": "searchable",
            "line": 29,
            "short_desc": "",
            "long_desc": "",
            "hint": null,
            "hint_desc": null,
            "tags": [],
            "modifiers": 9,
            "default": {
                "nodeType": "Expr_Array",
                "items": [],
                "attributes": {
                    "startLine": 29,
                    "endLine": 29,
                    "kind": 2
                }
            },
            "errors": []
        },
        "casts": {
            "name": "casts",
            "line": 31,
            "short_desc": "",
            "long_desc": "",
            "hint": null,
            "hint_desc": null,
            "tags": [],
            "modifiers": 2,
            "default": {
                "nodeType": "Expr_Array",
                "items": [
                    {
                        "nodeType": "Expr_ArrayItem",
                        "key": {
                            "nodeType": "Scalar_String",
                            "value": "details",
                            "attributes": {
                                "startLine": 32,
                                "endLine": 32,
                                "kind": 1
                            }
                        },
                        "value": {
                            "nodeType": "Scalar_String",
                            "value": "array",
                            "attributes": {
                                "startLine": 32,
                                "endLine": 32,
                                "kind": 1
                            }
                        },
                        "byRef": false,
                        "attributes": {
                            "startLine": 32,
                            "endLine": 32
                        }
                    }
                ],
                "attributes": {
                    "startLine": 31,
                    "endLine": 33,
                    "kind": 2
                }
            },
            "errors": []
        },
        "group": {
            "name": "group",
            "line": 21,
            "short_desc": "",
            "long_desc": null,
            "hint": [
                [
                    "string",
                    false
                ]
            ],
            "hint_desc": null,
            "tags": [],
            "modifiers": null,
            "default": null,
            "errors": []
        },
        "quantity_to_create": {
            "name": "quantity_to_create",
            "line": 21,
            "short_desc": "",
            "long_desc": null,
            "hint": [
                [
                    "integer",
                    false
                ]
            ],
            "hint_desc": null,
            "tags": [],
            "modifiers": null,
            "default": null,
            "errors": []
        },
        "role_convention": {
            "name": "role_convention",
            "line": 21,
            "short_desc": "",
            "long_desc": null,
            "hint": [
                [
                    "string",
                    false
                ]
            ],
            "hint_desc": null,
            "tags": [],
            "modifiers": null,
            "default": null,
            "errors": []
        },
        "channel_server": {
            "name": "channel_server",
            "line": 21,
            "short_desc": "",
            "long_desc": null,
            "hint": [
                [
                    "string",
                    false
                ]
            ],
            "hint_desc": null,
            "tags": [],
            "modifiers": null,
            "default": null,
            "errors": []
        },
        "aggregation_server": {
            "name": "aggregation_server",
            "line": 21,
            "short_desc": "",
            "long_desc": null,
            "hint": [
                [
                    "string",
                    false
                ]
            ],
            "hint_desc": null,
            "tags": [],
            "modifiers": null,
            "default": null,
            "errors": []
        },
        "env": {
            "name": "env",
            "line": 21,
            "short_desc": "",
            "long_desc": null,
            "hint": [
                [
                    "string",
                    false
                ]
            ],
            "hint_desc": null,
            "tags": [],
            "modifiers": null,
            "default": null,
            "errors": []
        },
        "details": {
            "name": "details",
            "line": 21,
            "short_desc": "",
            "long_desc": null,
            "hint": [
                [
                    "\\App\\text",
                    false
                ]
            ],
            "hint_desc": null,
            "tags": [],
            "modifiers": null,
            "default": null,
            "errors": []
        },
        "notes": {
            "name": "notes",
            "line": 21,
            "short_desc": "",
            "long_desc": null,
            "hint": [
                [
                    "\\App\\text",
                    false
                ]
            ],
            "hint_desc": null,
            "tags": [],
            "modifiers": null,
            "default": null,
            "errors": []
        },
        "cs_token": {
            "name": "cs_token",
            "line": 21,
            "short_desc": "",
            "long_desc": null,
            "hint": [
                [
                    "string",
                    false
                ]
            ],
            "hint_desc": null,
            "tags": [],
            "modifiers": null,
            "default": null,
            "errors": []
        }
    },
    "methods": {
        "boot": {
            "name": "boot",
            "line": 35,
            "short_desc": "",
            "long_desc": "",
            "hint": null,
            "hint_desc": null,
            "tags": [],
            "modifiers": 9,
            "is_by_ref": "",
            "exceptions": [],
            "errors": [],
            "parameters": []
        },
        "setGroupIdAttribute": {
            "name": "setGroupIdAttribute",
            "line": 47,
            "short_desc": "Set to null if empty",
            "long_desc": "",
            "hint": null,
            "hint_desc": null,
            "tags": [],
            "modifiers": 1,
            "is_by_ref": "",
            "exceptions": [],
            "errors": [],
            "parameters": {
                "input": {
                    "name": "input",
                    "line": 47,
                    "short_desc": "",
                    "long_desc": null,
                    "hint": [],
                    "tags": [],
                    "modifiers": null,
                    "default": null,
                    "variadic": false,
                    "is_by_ref": false
                }
            }
        },
        "setQuantityToCreateAttribute": {
            "name": "setQuantityToCreateAttribute",
            "line": 56,
            "short_desc": "Set attribute to money format",
            "long_desc": "",
            "hint": null,
            "hint_desc": null,
            "tags": [],
            "modifiers": 1,
            "is_by_ref": "",
            "exceptions": [],
            "errors": [],
            "parameters": {
                "input": {
                    "name": "input",
                    "line": 56,
                    "short_desc": "",
                    "long_desc": null,
                    "hint": [],
                    "tags": [],
                    "modifiers": null,
                    "default": null,
                    "variadic": false,
                    "is_by_ref": false
                }
            }
        },
        "setRoleConventionIdAttribute": {
            "name": "setRoleConventionIdAttribute",
            "line": 65,
            "short_desc": "Set to null if empty",
            "long_desc": "",
            "hint": null,
            "hint_desc": null,
            "tags": [],
            "modifiers": 1,
            "is_by_ref": "",
            "exceptions": [],
            "errors": [],
            "parameters": {
                "input": {
                    "name": "input",
                    "line": 65,
                    "short_desc": "",
                    "long_desc": null,
                    "hint": [],
                    "tags": [],
                    "modifiers": null,
                    "default": null,
                    "variadic": false,
                    "is_by_ref": false
                }
            }
        },
        "setChannelServerIdAttribute": {
            "name": "setChannelServerIdAttribute",
            "line": 74,
            "short_desc": "Set to null if empty",
            "long_desc": "",
            "hint": null,
            "hint_desc": null,
            "tags": [],
            "modifiers": 1,
            "is_by_ref": "",
            "exceptions": [],
            "errors": [],
            "parameters": {
                "input": {
                    "name": "input",
                    "line": 74,
                    "short_desc": "",
                    "long_desc": null,
                    "hint": [],
                    "tags": [],
                    "modifiers": null,
                    "default": null,
                    "variadic": false,
                    "is_by_ref": false
                }
            }
        },
        "setAggregationServerIdAttribute": {
            "name": "setAggregationServerIdAttribute",
            "line": 83,
            "short_desc": "Set to null if empty",
            "long_desc": "",
            "hint": null,
            "hint_desc": null,
            "tags": [],
            "modifiers": 1,
            "is_by_ref": "",
            "exceptions": [],
            "errors": [],
            "parameters": {
                "input": {
                    "name": "input",
                    "line": 83,
                    "short_desc": "",
                    "long_desc": null,
                    "hint": [],
                    "tags": [],
                    "modifiers": null,
                    "default": null,
                    "variadic": false,
                    "is_by_ref": false
                }
            }
        },
        "setEnvIdAttribute": {
            "name": "setEnvIdAttribute",
            "line": 92,
            "short_desc": "Set to null if empty",
            "long_desc": "",
            "hint": null,
            "hint_desc": null,
            "tags": [],
            "modifiers": 1,
            "is_by_ref": "",
            "exceptions": [],
            "errors": [],
            "parameters": {
                "input": {
                    "name": "input",
                    "line": 92,
                    "short_desc": "",
                    "long_desc": null,
                    "hint": [],
                    "tags": [],
                    "modifiers": null,
                    "default": null,
                    "variadic": false,
                    "is_by_ref": false
                }
            }
        },
        "group": {
            "name": "group",
            "line": 97,
            "short_desc": "",
            "long_desc": "",
            "hint": null,
            "hint_desc": null,
            "tags": [],
            "modifiers": 1,
            "is_by_ref": "",
            "exceptions": [],
            "errors": [],
            "parameters": []
        },
        "role_convention": {
            "name": "role_convention",
            "line": 102,
            "short_desc": "",
            "long_desc": "",
            "hint": null,
            "hint_desc": null,
            "tags": [],
            "modifiers": 1,
            "is_by_ref": "",
            "exceptions": [],
            "errors": [],
            "parameters": []
        },
        "channel_server": {
            "name": "channel_server",
            "line": 107,
            "short_desc": "",
            "long_desc": "",
            "hint": null,
            "hint_desc": null,
            "tags": [],
            "modifiers": 1,
            "is_by_ref": "",
            "exceptions": [],
            "errors": [],
            "parameters": []
        },
        "aggregation_server": {
            "name": "aggregation_server",
            "line": 112,
            "short_desc": "",
            "long_desc": "",
            "hint": null,
            "hint_desc": null,
            "tags": [],
            "modifiers": 1,
            "is_by_ref": "",
            "exceptions": [],
            "errors": [],
            "parameters": []
        },
        "env": {
            "name": "env",
            "line": 117,
            "short_desc": "",
            "long_desc": "",
            "hint": null,
            "hint_desc": null,
            "tags": [],
            "modifiers": 1,
            "is_by_ref": "",
            "exceptions": [],
            "errors": [],
            "parameters": []
        },
        "hosts": {
            "name": "hosts",
            "line": 122,
            "short_desc": "",
            "long_desc": "",
            "hint": null,
            "hint_desc": null,
            "tags": [],
            "modifiers": 1,
            "is_by_ref": "",
            "exceptions": [],
            "errors": [],
            "parameters": []
        }
    },
    "constants": []
}