{
    "name": "Illuminate\\Support\\Facades\\Gate",
    "line": 5667,
    "short_desc": "",
    "long_desc": "",
    "hint": null,
    "tags": {
        "see": [
            [
                "\\Illuminate\\Contracts\\Auth\\Access\\Gate"
            ]
        ]
    },
    "namespace": "Illuminate\\Support\\Facades",
    "file": "\/home\/vagrant\/repos\/cms\/configuration2\/_ide_helper.php",
    "relative_file": null,
    "hash": "1857e58d913c6ac5af7c2253be6a4f39eee9ad3d",
    "parent": null,
    "modifiers": 0,
    "is_trait": false,
    "is_interface": false,
    "aliases": [],
    "errors": [],
    "interfaces": [],
    "traits": [],
    "properties": [],
    "methods": {
        "has": {
            "name": "has",
            "line": 5676,
            "short_desc": "Determine if a given ability has been defined.",
            "long_desc": "",
            "hint": [
                [
                    "bool",
                    false
                ]
            ],
            "hint_desc": "",
            "tags": {
                "static": [
                    [
                        ""
                    ]
                ]
            },
            "modifiers": 9,
            "is_by_ref": "",
            "exceptions": [],
            "errors": [],
            "parameters": {
                "ability": {
                    "name": "ability",
                    "line": 5676,
                    "short_desc": "",
                    "long_desc": null,
                    "hint": [
                        [
                            "string",
                            false
                        ],
                        [
                            "array",
                            false
                        ]
                    ],
                    "tags": [],
                    "modifiers": null,
                    "default": null,
                    "variadic": false,
                    "is_by_ref": false
                }
            }
        },
        "define": {
            "name": "define",
            "line": 5691,
            "short_desc": "Define a new ability.",
            "long_desc": "",
            "hint": [
                [
                    "\\Illuminate\\Auth\\Access\\Gate",
                    false
                ]
            ],
            "hint_desc": "",
            "tags": {
                "static": [
                    [
                        ""
                    ]
                ]
            },
            "modifiers": 9,
            "is_by_ref": "",
            "exceptions": [
                [
                    "\\InvalidArgumentException",
                    ""
                ]
            ],
            "errors": [],
            "parameters": {
                "ability": {
                    "name": "ability",
                    "line": 5691,
                    "short_desc": "",
                    "long_desc": null,
                    "hint": [
                        [
                            "string",
                            false
                        ]
                    ],
                    "tags": [],
                    "modifiers": null,
                    "default": null,
                    "variadic": false,
                    "is_by_ref": false
                },
                "callback": {
                    "name": "callback",
                    "line": 5691,
                    "short_desc": "",
                    "long_desc": null,
                    "hint": [
                        [
                            "callable",
                            false
                        ],
                        [
                            "string",
                            false
                        ]
                    ],
                    "tags": [],
                    "modifiers": null,
                    "default": null,
                    "variadic": false,
                    "is_by_ref": false
                }
            }
        },
        "resource": {
            "name": "resource",
            "line": 5706,
            "short_desc": "Define abilities for a resource.",
            "long_desc": "",
            "hint": [
                [
                    "\\Illuminate\\Auth\\Access\\Gate",
                    false
                ]
            ],
            "hint_desc": "",
            "tags": {
                "static": [
                    [
                        ""
                    ]
                ]
            },
            "modifiers": 9,
            "is_by_ref": "",
            "exceptions": [],
            "errors": [],
            "parameters": {
                "name": {
                    "name": "name",
                    "line": 5706,
                    "short_desc": "",
                    "long_desc": null,
                    "hint": [
                        [
                            "string",
                            false
                        ]
                    ],
                    "tags": [],
                    "modifiers": null,
                    "default": null,
                    "variadic": false,
                    "is_by_ref": false
                },
                "class": {
                    "name": "class",
                    "line": 5706,
                    "short_desc": "",
                    "long_desc": null,
                    "hint": [
                        [
                            "string",
                            false
                        ]
                    ],
                    "tags": [],
                    "modifiers": null,
                    "default": null,
                    "variadic": false,
                    "is_by_ref": false
                },
                "abilities": {
                    "name": "abilities",
                    "line": 5706,
                    "short_desc": "",
                    "long_desc": null,
                    "hint": [
                        [
                            "array",
                            false
                        ],
                        [
                            "null",
                            false
                        ]
                    ],
                    "tags": [],
                    "modifiers": null,
                    "default": "null",
                    "variadic": false,
                    "is_by_ref": false
                }
            }
        },
        "policy": {
            "name": "policy",
            "line": 5720,
            "short_desc": "Define a policy class for a given class type.",
            "long_desc": "",
            "hint": [
                [
                    "\\Illuminate\\Auth\\Access\\Gate",
                    false
                ]
            ],
            "hint_desc": "",
            "tags": {
                "static": [
                    [
                        ""
                    ]
                ]
            },
            "modifiers": 9,
            "is_by_ref": "",
            "exceptions": [],
            "errors": [],
            "parameters": {
                "class": {
                    "name": "class",
                    "line": 5720,
                    "short_desc": "",
                    "long_desc": null,
                    "hint": [
                        [
                            "string",
                            false
                        ]
                    ],
                    "tags": [],
                    "modifiers": null,
                    "default": null,
                    "variadic": false,
                    "is_by_ref": false
                },
                "policy": {
                    "name": "policy",
                    "line": 5720,
                    "short_desc": "",
                    "long_desc": null,
                    "hint": [
                        [
                            "string",
                            false
                        ]
                    ],
                    "tags": [],
                    "modifiers": null,
                    "default": null,
                    "variadic": false,
                    "is_by_ref": false
                }
            }
        },
        "before": {
            "name": "before",
            "line": 5733,
            "short_desc": "Register a callback to run before all Gate checks.",
            "long_desc": "",
            "hint": [
                [
                    "\\Illuminate\\Auth\\Access\\Gate",
                    false
                ]
            ],
            "hint_desc": "",
            "tags": {
                "static": [
                    [
                        ""
                    ]
                ]
            },
            "modifiers": 9,
            "is_by_ref": "",
            "exceptions": [],
            "errors": [],
            "parameters": {
                "callback": {
                    "name": "callback",
                    "line": 5733,
                    "short_desc": "",
                    "long_desc": null,
                    "hint": [
                        [
                            "callable",
                            false
                        ]
                    ],
                    "tags": [],
                    "modifiers": null,
                    "default": null,
                    "variadic": false,
                    "is_by_ref": false
                }
            }
        },
        "after": {
            "name": "after",
            "line": 5746,
            "short_desc": "Register a callback to run after all Gate checks.",
            "long_desc": "",
            "hint": [
                [
                    "\\Illuminate\\Auth\\Access\\Gate",
                    false
                ]
            ],
            "hint_desc": "",
            "tags": {
                "static": [
                    [
                        ""
                    ]
                ]
            },
            "modifiers": 9,
            "is_by_ref": "",
            "exceptions": [],
            "errors": [],
            "parameters": {
                "callback": {
                    "name": "callback",
                    "line": 5746,
                    "short_desc": "",
                    "long_desc": null,
                    "hint": [
                        [
                            "callable",
                            false
                        ]
                    ],
                    "tags": [],
                    "modifiers": null,
                    "default": null,
                    "variadic": false,
                    "is_by_ref": false
                }
            }
        },
        "allows": {
            "name": "allows",
            "line": 5760,
            "short_desc": "Determine if the given ability should be granted for the current user.",
            "long_desc": "",
            "hint": [
                [
                    "bool",
                    false
                ]
            ],
            "hint_desc": "",
            "tags": {
                "static": [
                    [
                        ""
                    ]
                ]
            },
            "modifiers": 9,
            "is_by_ref": "",
            "exceptions": [],
            "errors": [],
            "parameters": {
                "ability": {
                    "name": "ability",
                    "line": 5760,
                    "short_desc": "",
                    "long_desc": null,
                    "hint": [
                        [
                            "string",
                            false
                        ]
                    ],
                    "tags": [],
                    "modifiers": null,
                    "default": null,
                    "variadic": false,
                    "is_by_ref": false
                },
                "arguments": {
                    "name": "arguments",
                    "line": 5760,
                    "short_desc": "",
                    "long_desc": null,
                    "hint": [
                        [
                            "array",
                            false
                        ],
                        [
                            "mixed",
                            false
                        ]
                    ],
                    "tags": [],
                    "modifiers": null,
                    "default": "array()",
                    "variadic": false,
                    "is_by_ref": false
                }
            }
        },
        "denies": {
            "name": "denies",
            "line": 5774,
            "short_desc": "Determine if the given ability should be denied for the current user.",
            "long_desc": "",
            "hint": [
                [
                    "bool",
                    false
                ]
            ],
            "hint_desc": "",
            "tags": {
                "static": [
                    [
                        ""
                    ]
                ]
            },
            "modifiers": 9,
            "is_by_ref": "",
            "exceptions": [],
            "errors": [],
            "parameters": {
                "ability": {
                    "name": "ability",
                    "line": 5774,
                    "short_desc": "",
                    "long_desc": null,
                    "hint": [
                        [
                            "string",
                            false
                        ]
                    ],
                    "tags": [],
                    "modifiers": null,
                    "default": null,
                    "variadic": false,
                    "is_by_ref": false
                },
                "arguments": {
                    "name": "arguments",
                    "line": 5774,
                    "short_desc": "",
                    "long_desc": null,
                    "hint": [
                        [
                            "array",
                            false
                        ],
                        [
                            "mixed",
                            false
                        ]
                    ],
                    "tags": [],
                    "modifiers": null,
                    "default": "array()",
                    "variadic": false,
                    "is_by_ref": false
                }
            }
        },
        "check": {
            "name": "check",
            "line": 5788,
            "short_desc": "Determine if all of the given abilities should be granted for the current user.",
            "long_desc": "",
            "hint": [
                [
                    "bool",
                    false
                ]
            ],
            "hint_desc": "",
            "tags": {
                "static": [
                    [
                        ""
                    ]
                ]
            },
            "modifiers": 9,
            "is_by_ref": "",
            "exceptions": [],
            "errors": [],
            "parameters": {
                "abilities": {
                    "name": "abilities",
                    "line": 5788,
                    "short_desc": "",
                    "long_desc": null,
                    "hint": [
                        [
                            "\\Illuminate\\Auth\\Access\\iterable",
                            false
                        ],
                        [
                            "string",
                            false
                        ]
                    ],
                    "tags": [],
                    "modifiers": null,
                    "default": null,
                    "variadic": false,
                    "is_by_ref": false
                },
                "arguments": {
                    "name": "arguments",
                    "line": 5788,
                    "short_desc": "",
                    "long_desc": null,
                    "hint": [
                        [
                            "array",
                            false
                        ],
                        [
                            "mixed",
                            false
                        ]
                    ],
                    "tags": [],
                    "modifiers": null,
                    "default": "array()",
                    "variadic": false,
                    "is_by_ref": false
                }
            }
        },
        "any": {
            "name": "any",
            "line": 5802,
            "short_desc": "Determine if any one of the given abilities should be granted for the current user.",
            "long_desc": "",
            "hint": [
                [
                    "bool",
                    false
                ]
            ],
            "hint_desc": "",
            "tags": {
                "static": [
                    [
                        ""
                    ]
                ]
            },
            "modifiers": 9,
            "is_by_ref": "",
            "exceptions": [],
            "errors": [],
            "parameters": {
                "abilities": {
                    "name": "abilities",
                    "line": 5802,
                    "short_desc": "",
                    "long_desc": null,
                    "hint": [
                        [
                            "\\Illuminate\\Auth\\Access\\iterable",
                            false
                        ],
                        [
                            "string",
                            false
                        ]
                    ],
                    "tags": [],
                    "modifiers": null,
                    "default": null,
                    "variadic": false,
                    "is_by_ref": false
                },
                "arguments": {
                    "name": "arguments",
                    "line": 5802,
                    "short_desc": "",
                    "long_desc": null,
                    "hint": [
                        [
                            "array",
                            false
                        ],
                        [
                            "mixed",
                            false
                        ]
                    ],
                    "tags": [],
                    "modifiers": null,
                    "default": "array()",
                    "variadic": false,
                    "is_by_ref": false
                }
            }
        },
        "none": {
            "name": "none",
            "line": 5816,
            "short_desc": "Determine if all of the given abilities should be denied for the current user.",
            "long_desc": "",
            "hint": [
                [
                    "bool",
                    false
                ]
            ],
            "hint_desc": "",
            "tags": {
                "static": [
                    [
                        ""
                    ]
                ]
            },
            "modifiers": 9,
            "is_by_ref": "",
            "exceptions": [],
            "errors": [],
            "parameters": {
                "abilities": {
                    "name": "abilities",
                    "line": 5816,
                    "short_desc": "",
                    "long_desc": null,
                    "hint": [
                        [
                            "\\Illuminate\\Auth\\Access\\iterable",
                            false
                        ],
                        [
                            "string",
                            false
                        ]
                    ],
                    "tags": [],
                    "modifiers": null,
                    "default": null,
                    "variadic": false,
                    "is_by_ref": false
                },
                "arguments": {
                    "name": "arguments",
                    "line": 5816,
                    "short_desc": "",
                    "long_desc": null,
                    "hint": [
                        [
                            "array",
                            false
                        ],
                        [
                            "mixed",
                            false
                        ]
                    ],
                    "tags": [],
                    "modifiers": null,
                    "default": "array()",
                    "variadic": false,
                    "is_by_ref": false
                }
            }
        },
        "authorize": {
            "name": "authorize",
            "line": 5831,
            "short_desc": "Determine if the given ability should be granted for the current user.",
            "long_desc": "",
            "hint": [
                [
                    "\\Illuminate\\Auth\\Access\\Response",
                    false
                ]
            ],
            "hint_desc": "",
            "tags": {
                "static": [
                    [
                        ""
                    ]
                ]
            },
            "modifiers": 9,
            "is_by_ref": "",
            "exceptions": [
                [
                    "\\Illuminate\\Auth\\Access\\AuthorizationException",
                    ""
                ]
            ],
            "errors": [],
            "parameters": {
                "ability": {
                    "name": "ability",
                    "line": 5831,
                    "short_desc": "",
                    "long_desc": null,
                    "hint": [
                        [
                            "string",
                            false
                        ]
                    ],
                    "tags": [],
                    "modifiers": null,
                    "default": null,
                    "variadic": false,
                    "is_by_ref": false
                },
                "arguments": {
                    "name": "arguments",
                    "line": 5831,
                    "short_desc": "",
                    "long_desc": null,
                    "hint": [
                        [
                            "array",
                            false
                        ],
                        [
                            "mixed",
                            false
                        ]
                    ],
                    "tags": [],
                    "modifiers": null,
                    "default": "array()",
                    "variadic": false,
                    "is_by_ref": false
                }
            }
        },
        "raw": {
            "name": "raw",
            "line": 5845,
            "short_desc": "Get the raw result from the authorization callback.",
            "long_desc": "",
            "hint": [
                [
                    "mixed",
                    false
                ]
            ],
            "hint_desc": "",
            "tags": {
                "static": [
                    [
                        ""
                    ]
                ]
            },
            "modifiers": 9,
            "is_by_ref": "",
            "exceptions": [],
            "errors": [],
            "parameters": {
                "ability": {
                    "name": "ability",
                    "line": 5845,
                    "short_desc": "",
                    "long_desc": null,
                    "hint": [
                        [
                            "string",
                            false
                        ]
                    ],
                    "tags": [],
                    "modifiers": null,
                    "default": null,
                    "variadic": false,
                    "is_by_ref": false
                },
                "arguments": {
                    "name": "arguments",
                    "line": 5845,
                    "short_desc": "",
                    "long_desc": null,
                    "hint": [
                        [
                            "array",
                            false
                        ],
                        [
                            "mixed",
                            false
                        ]
                    ],
                    "tags": [],
                    "modifiers": null,
                    "default": "array()",
                    "variadic": false,
                    "is_by_ref": false
                }
            }
        },
        "getPolicyFor": {
            "name": "getPolicyFor",
            "line": 5858,
            "short_desc": "Get a policy instance for a given class.",
            "long_desc": "",
            "hint": [
                [
                    "mixed",
                    false
                ]
            ],
            "hint_desc": "",
            "tags": {
                "static": [
                    [
                        ""
                    ]
                ]
            },
            "modifiers": 9,
            "is_by_ref": "",
            "exceptions": [],
            "errors": [],
            "parameters": {
                "class": {
                    "name": "class",
                    "line": 5858,
                    "short_desc": "",
                    "long_desc": null,
                    "hint": [
                        [
                            "object",
                            false
                        ],
                        [
                            "string",
                            false
                        ]
                    ],
                    "tags": [],
                    "modifiers": null,
                    "default": null,
                    "variadic": false,
                    "is_by_ref": false
                }
            }
        },
        "guessPolicyNamesUsing": {
            "name": "guessPolicyNamesUsing",
            "line": 5871,
            "short_desc": "Specify a callback to be used to guess policy names.",
            "long_desc": "",
            "hint": [
                [
                    "\\Illuminate\\Auth\\Access\\Gate",
                    false
                ]
            ],
            "hint_desc": "",
            "tags": {
                "static": [
                    [
                        ""
                    ]
                ]
            },
            "modifiers": 9,
            "is_by_ref": "",
            "exceptions": [],
            "errors": [],
            "parameters": {
                "callback": {
                    "name": "callback",
                    "line": 5871,
                    "short_desc": "",
                    "long_desc": null,
                    "hint": [
                        [
                            "callable",
                            false
                        ]
                    ],
                    "tags": [],
                    "modifiers": null,
                    "default": null,
                    "variadic": false,
                    "is_by_ref": false
                }
            }
        },
        "resolvePolicy": {
            "name": "resolvePolicy",
            "line": 5885,
            "short_desc": "Build a policy class instance of the given type.",
            "long_desc": "",
            "hint": [
                [
                    "mixed",
                    false
                ]
            ],
            "hint_desc": "",
            "tags": {
                "static": [
                    [
                        ""
                    ]
                ]
            },
            "modifiers": 9,
            "is_by_ref": "",
            "exceptions": [
                [
                    "\\Illuminate\\Contracts\\Container\\BindingResolutionException",
                    ""
                ]
            ],
            "errors": [],
            "parameters": {
                "class": {
                    "name": "class",
                    "line": 5885,
                    "short_desc": "",
                    "long_desc": null,
                    "hint": [
                        [
                            "object",
                            false
                        ],
                        [
                            "string",
                            false
                        ]
                    ],
                    "tags": [],
                    "modifiers": null,
                    "default": null,
                    "variadic": false,
                    "is_by_ref": false
                }
            }
        },
        "forUser": {
            "name": "forUser",
            "line": 5898,
            "short_desc": "Get a gate instance for the given user.",
            "long_desc": "",
            "hint": [
                [
                    "Illuminate\\Support\\Facades\\Gate",
                    false
                ]
            ],
            "hint_desc": "",
            "tags": {
                "static": [
                    [
                        ""
                    ]
                ]
            },
            "modifiers": 9,
            "is_by_ref": "",
            "exceptions": [],
            "errors": [],
            "parameters": {
                "user": {
                    "name": "user",
                    "line": 5898,
                    "short_desc": "",
                    "long_desc": null,
                    "hint": [
                        [
                            "\\Illuminate\\Contracts\\Auth\\Authenticatable",
                            false
                        ],
                        [
                            "mixed",
                            false
                        ]
                    ],
                    "tags": [],
                    "modifiers": null,
                    "default": null,
                    "variadic": false,
                    "is_by_ref": false
                }
            }
        },
        "abilities": {
            "name": "abilities",
            "line": 5910,
            "short_desc": "Get all of the defined abilities.",
            "long_desc": "",
            "hint": [
                [
                    "array",
                    false
                ]
            ],
            "hint_desc": "",
            "tags": {
                "static": [
                    [
                        ""
                    ]
                ]
            },
            "modifiers": 9,
            "is_by_ref": "",
            "exceptions": [],
            "errors": [],
            "parameters": []
        },
        "policies": {
            "name": "policies",
            "line": 5922,
            "short_desc": "Get all of the defined policies.",
            "long_desc": "",
            "hint": [
                [
                    "array",
                    false
                ]
            ],
            "hint_desc": "",
            "tags": {
                "static": [
                    [
                        ""
                    ]
                ]
            },
            "modifiers": 9,
            "is_by_ref": "",
            "exceptions": [],
            "errors": [],
            "parameters": []
        }
    },
    "constants": []
}